Metadata-Version: 2.1
Name: testghapythonpackage
Version: 0.0.5
Summary: Add short description here
Maintainer-email: Your Name <your@email.com>
License: MIT
Classifier: Programming Language :: Python :: 3
Classifier: Operating System :: OS Independent
Classifier: License :: OSI Approved :: MIT License
Requires-Python: >=3.8
Provides-Extra: tests
Provides-Extra: docs
License-File: LICENSE.md
